copied.py
discordapiwebhooks/discordapiwebhooks.py
discordapiwebhooks/setup.py
phpdiscord/phpdiscord.py
copied-0.1.2.dist-info/METADATA
copied-0.1.2.dist-info/WHEEL
copied-0.1.2.dist-info/top_level.txt
copied-0.1.2.dist-info/RECORD
