Metadata-Version: 2.1
Name: copied
Version: 0.1.2
Summary: A module for copying bot with IDs, events and commands for Discord API
Home-page: UNKNOWN
License: UNKNOWN
Platform: UNKNOWN
